selector_ai_etcd/__init__.py
selector_ai_etcd/__main__.py
selector_ai_etcd/selector_ai_etcd.py
selector_ai_etcd-1.1.0.dist-info/LICENSE
selector_ai_etcd-1.1.0.dist-info/METADATA
selector_ai_etcd-1.1.0.dist-info/WHEEL
selector_ai_etcd-1.1.0.dist-info/entry_points.txt
selector_ai_etcd-1.1.0.dist-info/top_level.txt
selector_ai_etcd-1.1.0.dist-info/RECORD
