Metadata-Version: 2.1
Name: selector-ai-etcd
Version: 1.1.0
Summary: Selector AI etcd
Home-page: UNKNOWN
Author: Rohit Kumar
Author-email: rohit.kumar@selector.ai
License: MIT
Platform: UNKNOWN
Classifier: License :: OSI Approved :: MIT License
Classifier: Programming Language :: Python
Classifier: Programming Language :: Python :: 3
License-File: LICENSE
Requires-Dist: etcd3
